{"$schema":"https://vega.github.io/schema/vega-lite/v5.json","description":"Occupancy rates of rooms","data":{"values":[{"roomCode":"B103","occupiedHours":42,"capacity":{}},{"roomCode":"P101","occupiedHours":38,"capacity":{}},{"roomCode":"S104","occupiedHours":33,"capacity":{}},{"roomCode":"A001","occupiedHours":33,"capacity":{}},{"roomCode":"S203","occupiedHours":40,"capacity":{}},{"roomCode":"A207","occupiedHours":10,"capacity":{}},{"roomCode":"S103","occupiedHours":37.5,"capacity":{}},{"roomCode":"P103","occupiedHours":32,"capacity":{}},{"roomCode":"B207","occupiedHours":17,"capacity":{}},{"roomCode":"A105","occupiedHours":25.5,"capacity":{}},{"roomCode":"S204","occupiedHours":34,"capacity":{}},{"roomCode":"A203","occupiedHours":13,"capacity":{}},{"roomCode":"B210","occupiedHours":8,"capacity":{}},{"roomCode":"B001","occupiedHours":12,"capacity":{}},{"roomCode":"C002","occupiedHours":34.5,"capacity":{}},{"roomCode":"B201","occupiedHours":31,"capacity":{}},{"roomCode":"B007","occupiedHours":15,"capacity":{}},{"roomCode":"B204","occupiedHours":17,"capacity":{}},{"roomCode":"B101","occupiedHours":44,"capacity":{}},{"roomCode":"C202","occupiedHours":6,"capacity":{}},{"roomCode":"C204","occupiedHours":26,"capacity":{}},{"roomCode":"C105","occupiedHours":26,"capacity":{}},{"roomCode":"A205","occupiedHours":22,"capacity":{}},{"roomCode":"EXT1","occupiedHours":93.5,"capacity":{}},{"roomCode":"P104","occupiedHours":37,"capacity":{}},{"roomCode":"A208","occupiedHours":18,"capacity":{}},{"roomCode":"A206","occupiedHours":23,"capacity":{}},{"roomCode":"C104","occupiedHours":20,"capacity":{}},{"roomCode":"P202","occupiedHours":38,"capacity":{}},{"roomCode":"M204","occupiedHours":6,"capacity":{}},{"roomCode":"B105","occupiedHours":22.5,"capacity":{}},{"roomCode":"S102","occupiedHours":34,"capacity":{}},{"roomCode":"D106","occupiedHours":15,"capacity":{}},{"roomCode":"J004","occupiedHours":12,"capacity":{}},{"roomCode":"C102","occupiedHours":17.5,"capacity":{}},{"roomCode":"S202","occupiedHours":23.5,"capacity":{}},{"roomCode":"B208","occupiedHours":18.5,"capacity":{}},{"roomCode":"P102","occupiedHours":32.5,"capacity":{}},{"roomCode":"S101","occupiedHours":38.5,"capacity":{}},{"roomCode":"S201","occupiedHours":40.5,"capacity":{}},{"roomCode":"P201","occupiedHours":29,"capacity":{}},{"roomCode":"A103","occupiedHours":19.5,"capacity":{}},{"roomCode":"B203","occupiedHours":25,"capacity":{}},{"roomCode":"B205","occupiedHours":23,"capacity":{}},{"roomCode":"N101","occupiedHours":22,"capacity":{}},{"roomCode":"M207","occupiedHours":20,"capacity":{}},{"roomCode":"C001","occupiedHours":17.5,"capacity":{}},{"roomCode":"M102","occupiedHours":14,"capacity":{}},{"roomCode":"A002","occupiedHours":12,"capacity":{}},{"roomCode":"P203","occupiedHours":45,"capacity":{}},{"roomCode":"B106","occupiedHours":15,"capacity":{}},{"roomCode":"B202","occupiedHours":37,"capacity":{}},{"roomCode":"C103","occupiedHours":24,"capacity":{}},{"roomCode":"C201","occupiedHours":16,"capacity":{}},{"roomCode":"C203","occupiedHours":26,"capacity":{}},{"roomCode":"C207","occupiedHours":26,"capacity":{}},{"roomCode":"C101","occupiedHours":2,"capacity":{}},{"roomCode":"C205","occupiedHours":18,"capacity":{}},{"roomCode":"C210","occupiedHours":20,"capacity":{}},{"roomCode":"C206","occupiedHours":14,"capacity":{}},{"roomCode":"C208","occupiedHours":18,"capacity":{}},{"roomCode":"D206","occupiedHours":17,"capacity":{}},{"roomCode":"D202","occupiedHours":39,"capacity":{}},{"roomCode":"D105","occupiedHours":15,"capacity":{}},{"roomCode":"J105","occupiedHours":8,"capacity":{}},{"roomCode":"A002/L :-0:00","occupiedHours":2,"capacity":{}},{"roomCode":"B210/L 16:00-18:00","occupiedHours":1,"capacity":{}},{"roomCode":"B210/J 14:00-16:00","occupiedHours":1,"capacity":{}},{"roomCode":"B210/ME 18:00-19:00","occupiedHours":2,"capacity":{}},{"roomCode":"P204","occupiedHours":23,"capacity":{}},{"roomCode":"J101","occupiedHours":14,"capacity":{}},{"roomCode":"A108","occupiedHours":34,"capacity":{}},{"roomCode":"J002","occupiedHours":30,"capacity":{}},{"roomCode":"D102","occupiedHours":18,"capacity":{}},{"roomCode":"A210","occupiedHours":21,"capacity":{}},{"roomCode":"J102","occupiedHours":8,"capacity":{}},{"roomCode":"A102","occupiedHours":14,"capacity":{}},{"roomCode":"B209","occupiedHours":11,"capacity":{}},{"roomCode":"A201","occupiedHours":16,"capacity":{}},{"roomCode":"D101","occupiedHours":18,"capacity":{}},{"roomCode":"","occupiedHours":6.5,"capacity":{}},{"roomCode":"A212","occupiedHours":8,"capacity":{}},{"roomCode":"D201","occupiedHours":30,"capacity":{}},{"roomCode":"D108","occupiedHours":3,"capacity":{}},{"roomCode":"M208","occupiedHours":12,"capacity":{}},{"roomCode":"SPOR","occupiedHours":4,"capacity":{}},{"roomCode":"G002","occupiedHours":8,"capacity":{}},{"roomCode":"IUT1","occupiedHours":8,"capacity":{}},{"roomCode":"D002","occupiedHours":9,"capacity":{}},{"roomCode":"B005","occupiedHours":4,"capacity":{}}]},"mark":"bar","encoding":{"x":{"field":"roomCode","type":"nominal","axis":{"labelAngle":-45}},"y":{"field":"occupiedHours","type":"quantitative"},"tooltip":[{"field":"roomCode","type":"nominal"},{"field":"occupiedHours","type":"quantitative"},{"field":"capacity","type":"quantitative"}]}}